Workbook

Sheet Relación con el cliente
A2: Tabla 3. Costos de gestión de relación con clientes
A3: Concepto | B3: Costo mensual | C3: Descripción
A4: Infraestructura de servidores (Vercel Pro + Render Starter) | B4: 47 | C4: Vercel Pro $20/usuario/mes (1 usuario) + Render Starter $7/servicio/mes (1 servicio activo) + Render DB basica $6/mes = $33 infraestructura base + $14 adicional estimado uso
A5: Herramientas de soporte (chatbot Gemini 2.5 Flash + Brevo) | B5: 25 | C5: Gemini 2.5 Flash: $0.10/mill. tokens input, estimado 100K tokens/mes = $0.01; Brevo Starter 5K emails/mes: $9; Brevo logo removal add-on: $9; total estimado soporte comunicacion: $25
A6: Personal de soporte tecnico (1 operador, tiempo parcial) | B6: 400 | C6: Sueldo mensual tiempo parcial equivalente en Guayaquil, perfil junior-mid soporte
A7: TOTAL MENSUAL GESTION DE RELACION | B7: =B4+B5+B6 -> 472 | C7: Incluye infraestructura, comunicación y personal de atención

Sheet Fuentes de ingresos
A2: Tabla 2. Fuentes de ingreso de NEXIA
A3: Fuente de Ingreso | B3: Descripción | C3: Precio base | D3: Contribución
A4: Suscripción o Licencia B2B (modelo principal) | B4: Entidades financieras pagan suscripción mensual o anual según volumen de solicitudes, usuarios operadores y funcionalidades contratadas. | C4: Desde $500/mes | D4: 0.6
A5: Ingresos por transacción/uso | B5: Comisión por operación exitosa dentro de la plataforma: solicitud de crédito procesada ($0.50), validación KYC ($0.33 costo Didit, diferencial cobrado), consulta financiera ($0.20). | C5: Desde $0.20/op | D5: 0.25
A6: Servicios de implementación y soporte | B6: Configuración inicial ($1,500 único), integración branding ($800), adaptación flujos ($1,000), capacitación ($500/sesión), soporte premium ($200/mes). | C6: Desde $200/mes | D6: 0.15
A8: Tabla 3. Planes de suscripción NEXIA
A9: Plan | B9: Precio mensual | C9: Solicitudes incluidas | D9: Funcionalidades principales
A10: Plan Básico | B10: $500/mes | C10: Hasta 1,000 solicitudes/mes | D10: KYC/AML básico (primeras 500 gratis vía Didit), panel operador, notificaciones email (Brevo Free)
A11: Plan Profesional | B11: $1,200/mes | C11: Hasta 5,000 solicitudes/mes | D11: KYC/AML avanzado, integración BCRA/AFIP, scoring automático, chatbot Gemini Flash
A12: Plan Empresarial | B12: $2,500/mes | C12: Ilimitadas | D12: Todas las funcionalidades + API personalizada, soporte 24/7, SLA 99.9%, branding blanco
A14: Tabla 4. Cobrar por tu producto
A15: Plan | B15: Precio mensual | C15: Solicitudes incluidas
A16: Plan Básico | B16: $500 | C16: Hasta 1,000 solicitudes/mes
A17: Plan Profesional | B17: $1,200 | C17: Hasta 5,000 solicitudes/mes
A18: Plan Empresarial | B18: $2,500 | C18: Ilimitadas

Sheet Recursos clave
A2: Tabla 7. Inventario de activos físicos y tecnológicos de NEXIA
A3: Categoría | B3: Elemento | C3: Cantidad | D3: Costo Unitario | E3: Costo Total
A4: Computación | B4: Laptops de desarrollo (16GB RAM, 512GB SSD) | C4: 3 | D4: 1200 | E4: =C4*D4 -> 3600
A5: Computación | B5: Monitores adicionales 24" | C5: 3 | D5: 200 | E5: =C5*D5 -> 600
A6: Computación | B6: Estaciones de trabajo (escritorio + silla ergonomica) | C6: 3 | D6: 400 | E6: =C6*D6 -> 1200
A7: Servidores | B7: Servidor de prueba y staging cloud reservado (deposito) | C7: 1 | D7: 500 | E7: =C7*D7 -> 500
A8: Redes | B8: Router alta velocidad + switch + cableado | C8: 1 | D8: 300 | E8: =C8*D8 -> 300
A9: Oficina | B9: Mobiliario de oficina | C9: 1 | D9: 400 | E9: =C9*D9 -> 400
A10: Oficina | B10: Suministros de oficina (papeleria, tinta) | C10: 1 | D10: 200 | E10: =C10*D10 -> 200
A11: Desarrollo | B11: Licencias herramientas desarrollo (GitHub Team 3 usuarios x 4 = 12/mes x 12 = deposito inicial) | C11: 3 | D11: 48 | E11: =C11*D11 -> 144
A12: Desarrollo | B12: Suscripcion diseño Figma Professional (2 editores x 15/mes x 12 = deposito inicial) | C12: 2 | D12: 180 | E12: =C12*D12 -> 360
A13: Seguridad | B13: Licencias software de seguridad y antivirus | C13: 3 | D13: 100 | E13: =C13*D13 -> 300
A14: TOTAL RECURSOS FISICOS | E14: =SUM(E4:E13) -> 7604
A16: Tabla 8. Precios de plataformas cloud utilizadas en NEXIA
A17: Servicio | B17: Plan / Precio | C17: Observación
A18: Vercel (frontend/despliegue) | B18: Free (Hobby): $0. Pro: $20/usuario/mes | C18: MVP usa plan Hobby gratuito. Producción requiere Pro a $20/mes por 1 usuario = $20/mes
A19: Render (backend API) | B19: Free: $0 (spin-down 15 min). Starter: $7/servicio/mes | C19: MVP usa Free. Producción: Starter $7/mes por servicio backend (1 servicio) + DB basica $6/mes = $13/mes
A20: Supabase (base de datos + auth) | B20: Free: $0 (500MB DB, 50K MAU). Pro: $25/proyecto/mes | C20: MVP usa Free. Producción requiere Pro a $25/mes (8GB DB, 100K MAU, 100GB storage)
A21: GitHub (control de versiones) | B21: Free: $0 (repos privados ilimitados). Team: $4/usuario/mes | C21: MVP usa Free. Producción: Team a $4/mes por usuario; 3 usuarios = $12/mes
A22: Figma (diseño UI/UX) | B22: Starter: $0 (3 archivos colaborativos). Professional: $15/editor/mes (mensual) o $12/editor/mes (anual) | C22: MVP usa Starter gratuito. Producción: Professional 2 editores x $15/mes = $30/mes (mensual) o $24/mes (anual)
A23: Brevo (email transaccional) | B23: Free: 9,000 emails/mes, 300/día. Starter: $9/mes desde 5K emails sin límite diario | C23: MVP usa Free. Producción: Starter $9/mes para emails sin límite diario + $9 add-on eliminar logo Brevo = $18/mes
A24: Google Gemini API (chatbot IA) | B24: Free: 15 RPM, 1,000 RPD (Gemini 2.5 Flash). Pago: $0.10/mill. tokens input, $0.40/mill. tokens output (Flash-Lite) | C24: MVP usa capa gratuita de AI Studio. Producción estimado 583 solicitudes/mes x 1,000 tokens promedio = 583K tokens/mes = $0.06 input + $0.23 output = aprox. $0.30/mes inicial
A25: Didit KYC (verificación identidad) | B25: Free: 500 verificaciones/mes gratis siempre. Pago: $0.33 por verificación completa (ID + Liveness + Face Match) | C25: MVP usa 500 gratis/mes. Producción: 583 solicitudes/mes - 500 gratis = 83 verificaciones x $0.33 = $27.39/mes en año 1
A27: Tabla 9. Recursos clave más costosos
A28: Recurso | B28: Costo mensual estimado | C28: Justificación
A29: Talento humano (desarrolladores senior tiempo parcial) | B29: $1,600 | C29: Personal calificado en tecnologías cloud y APIs financieras
A30: Infraestructura cloud (Vercel, Render, Supabase) | B30: $58 | C30: Escalabilidad y alta disponibilidad (99.9% uptime)
A31: APIs externas (Didit, BCRA, Brevo, Gemini) | B31: $153 (variable) | C31: Costo por uso que escala con el volumen de solicitudes

Sheet Actividades clave
A1: Tabla 10. actividades clave más costosos
A2: Actividad | B2: Costo mensual estimado | C2: Descripción
A3: Desarrollo y mantenimiento de software | B3: $1,600 | C3: Salarios de 2 desarrolladores full-stack tiempo parcial y QA
A4: Integración y monitoreo de APIs externas | B4: $153 | C4: Gestión de conexiones con Didit, BCRA, Brevo, Gemini
A5: Marketing y ventas B2B | B5: $200 | C5: Publicidad segmentada, eventos, creación de contenido

Sheet Preguntas adicionales a EC
A1: Tabla 12. Costos variables mensuales NEXIA - operación productiva año 1
A2: Concepto de Costo Variable | B2: Costo Unitario Real | C2: Volumen Mensual (Año 1) | D2: Costo Mensual | E2: Costo Anual
A3: Verificación KYC completa (Didit) | B3: 0.33 por verificación (real Didit pricing). MVP: 500 gratis/mes | C3: 583 solicitudes/mes. Cobradas: 583-500=83 | D3: 27 | E3: =D3*12 -> 324
A4: Consulta BCRA/buros crediticios (API financiera estimada) | B4: 0.20 por consulta (estimado mercado) | C4: 583 consultas/mes | D4: 117 | E4: =D4*12 -> 1404
A5: Envió de emails transaccionales (Brevo Starter) | B5: 9/mes plan Starter hasta 20K emails/mes. MVP: 9,000/mes gratis | C5: Hasta 20,000 emails (plan 9/mes; costo fijo) | D5: 9 | E5: =D5*12 -> 108
A6: Consumo IA Google Gemini 2.5 Flash (chatbot) | B6: 0.10/mill. tokens input + 0.40/mill. tokens output. MVP: gratuito hasta 1,000 RPD | C6: ~583K tokens/mes (1K tokens/solicitud promedio) | D6: 0.29 | E6: =D6*12 -> 3.48
A7: Almacenamiento documentos Supabase Pro (100GB incluidos) | B7: 0.021/GB adicional sobre 100GB incluidos en Pro 25/mes | C7: ~50GB/mes en año 1 (dentro del plan) | D7: 0 | E7: =D7*12 -> 0
A8: API validación email (Brevo incluido en plan Starter) | B8: 0 adicional (incluido en Brevo Starter) | C8: 583 validaciones/mes | D8: 0 | E8: =D8*12 -> 0
A9: Comisiones pasarela de pago (Stripe estimado) | B9: 2.9% + 0.30 por transacción | C9: ~5 transacciones/mes de 850 promedio = 4,250 facturado | D9: 154 | E9: =D9*12 -> 1848
A10: TOTAL COSTOS VARIABLES MENSUALES (producción) | D10: =SUM(D3:D9) -> 307.29 | E10: =SUM(E3:E9) -> 3687.48
A12: Tabla 13. Costos fijos mensuales NEXIA — operación productiva (precios 2025-2026)
A13: Concepto de Costo Fijo | B13: Detalle / Precio real verificado | C13: Costo Mensual | D13: Costo Anual
A14: Vercel Pro (1 usuario, frontend) | B14: 20/usuario/mes | C14: 20 | D14: =C14*12 -> 240
A15: Render Starter (1 servicio backend) + DB básica | B15: 7/servicio/mes (Starter) + 6/mes DB básica = 13/mes total | C15: 13 | D15: =C15*12 -> 156
A16: Supabase Pro (base de datos + auth) | B16: 25/proyecto/mes | C16: 25 | D16: =C16*12 -> 300
A17: GitHub Team (3 usuarios) | B17: 4/usuario/mes x 3 usuarios = 12/mes | C17: 12 | D17: =C17*12 -> 144
A18: Figma Professional (2 editores) | B18: 15/editor/mes x 2 = 30/mes (mensual). Si anual: 12/editor x 2 = 24/mes | C18: 30 | D18: =C18*12 -> 360
A19: Brevo Starter (emails + eliminar logo) | B19: 9/mes plan Starter 5K-20K emails + 9/mes add-on eliminar logo = 18/mes | C19: 18 | D19: =C19*12 -> 216
A20: Internet de alta velocidad (100 Mbps simétrico) | B20: Servicio ISP local Guayaquil estimado | C20: 30 | D20: =C20*12 -> 360
A21: Energía eléctrica (laboratorio/coworking) | B21: Estimado uso mensual oficina | C21: 40 | D21: =C21*12 -> 480
A22: Alquiler espacio coworking (año 1: remoto) | B22: Año 1: operación remota (0). Desde año 3: coworking ~150/mes | C22: 0 | D22: =C22*12 -> 0
A23: Salario desarrollador frontend (tiempo parcial) | B23: Perfil junior-mid, tiempo parcial, Guayaquil | C23: 600 | D23: =C23*12 -> 7200
A24: Salario desarrollador backend (tiempo parcial) | B24: Perfil junior-mid, tiempo parcial, Guayaquil | C24: 600 | D24: =C24*12 -> 7200
A25: Salario QA y soporte técnico (tiempo parcial) | B25: Perfil junior, tiempo parcial, Guayaquil | C25: 400 | D25: =C25*12 -> 4800
... A27: Gastos administrativos (papelería, comunicaciones) | B27: Gastos operativos generales | C27: 50 | D27: =C27*12 -> 600
A28: TOTAL COSTOS FIJOS MENSUALES | C28: =SUM(C14:C27) -> 2038 | D28: =SUM(D14:D27) -> 24456

Sheet Estructura de costos
A1: Tabla 11. Estructura de costes anuales NEXIA - Año 1
A2: Categoría de Costo | B2: Costo Mensual | C2: Costo Anual | D2: Porcentaje | K2: Tabla 16. Presupuesto de implementación NEXIA
A3: Costos fijos | B3: ='Preguntas adicionales a EC'!C28 -> 2038 | C3: ='Preguntas adicionales a EC'!D28 -> 24456 | D3: 0.87 | K3: Concepto de Inversión Inicial | L3: Monto
A4: Costos variables | B4: ='Preguntas adicionales a EC'!D10 -> 307.29 | C4: ='Preguntas adicionales a EC'!E10 -> 3687.48 | D4: 0.13 | K4: Desarrollo del MVP (3 meses de salarios parciales: 2 dev + 1 QA) | L4: 4800
A5: TOTAL COSTOS ANUALES | B5: =SUM(B3:B4) -> 2345.29 | C5: =SUM(C3:C4) -> 28143.48 | D5: 1 | K5: Equipos de desarrollo (3 laptops 1,200 c/u + 3 monitores 200 c/u) | L5: 4200
K6: Licencias anuales de software y herramientas (GitHub Team + Figma Pro) | L6: 504
A7: Tabla 14. Proyección de costos variables a 5 años (operación productiva) | K7: Marketing inicial y branding (logo, identidad visual, landing page) | L7: 500
A8: Año | B8: Solicitudes | C8: Factor | D8: KYC Didit (cobradas) | F8: Otros variables | G8: Total Costos Variables | K8: Gastos legales y registro de marca SENADI | L8: 300
A9: Año 1 | B9: 7000 | C9: 1.00 | D9: 328 (83 x 0.33 x 12) | E9: =83*0.33*12 -> 328.68 | F9: 3359 | G9: =SUM(E9:F9) -> 3687.68 | K9: Imprevistos (8% del subtotal) | L9: 841
A10: Año 2 | B10: 8000 | C10: 1.14 | D10: 666 (1,000 x 0.33 x 2 meses + resto) | E10: 666 | F10: 3838 | G10: =SUM(E10:F10) -> 4504 | K10: TOTAL INVERSION INICIAL | L10: =SUM(L4:L9) -> 11145
A11: Año 3 | B11: 9000 | C11: 1.29 | D11: 1,188 (300 x 0.33 x 12) | E11: =300*0.33*12 -> 1188 | F11: 4317 | G11: =SUM(E11:F11) -> 5505 | K11: Tabla 17. Capital de trabajo
A12: Año 4 | B12: 10000 | C12: 1.43 | D12: 1,584 (400 x 0.33 x 12) | E12: =400*0.33*12 -> 1584 | F12: 4796 | G12: =SUM(E12:F12) -> 6380 | K12: Concepto capital de trabajo | L12: Monto
A13: Año 5 | B13: 12000 | C13: 1.71 | D13: 2,376 (600 x 0.33 x 12) | E13: =600*0.33*12 -> 2376 | F13: 5754 | G13: =SUM(E13:F13) -> 8130 | K13: Costo operativo mensual con planes gratuitos (salarios + internet + electricidad + marketing) | L13: 1320
K14: Capital de trabajo para 3 meses | L14: 3960
A15: Tabla 15. Proyección de costos fijos anuales a 5 años | K15: INVERSION TOTAL REQUERIDA (11,145 + 3,960) | L15: =L10+L14 -> 15105
A16: Año | B16: Ajuste | C16: Costos Fijos Anuales
A17: Año 1 | B17: Operacion remota, sin alquiler de oficina | C17: 24.456
A18: Año 2 | B18: Sin cambios en costos fijos | C18: 24.456
A19: Año 3 | B19: Se incorpora alquiler coworking 150/mes = 1,800/año adicional | C19: 26.256
A20: Año 4 | B20: Sin cambios adicionales respecto al año 3 | C20: 26.256
A21: Año 5 | B21: Sin cambios adicionales respecto al año 4 | C21: 26.256

Sheet Proyeccion de ingresos
A1: Tabla 18. Proyección de ingresos año 1 — escenario base NEXIA
A3: Concepto | B3: Precio Unitario Promedio | C3: Ingresos Anuales (Año 1)
A4: Suscripción mensual promedio ponderado (mix de planes) | B4: 850 | C4: =B4*12 -> 10200
A5: Ingresos por transacción (0.50 x 7,000 solicitudes) | B5: 0.5 | C5: =0.5*7000 -> 3500
A6: Servicios de implementación y soporte (2 clientes x 1,250 prom.) 2,500 único + 200/mes | B6: 2,500 único + 200/mes | C6: =2500+(200*12) -> 4900
A7: INGRESOS TOTALES ANUALES AÑO 1 (escenario base gradual) | C7: 18.7
A9: Tabla 19. Costo Volumen Utilidad
A10: COSTO VOLUMEN UTILIDAD | B10: VALOR
A11: Ventas Anuales proyectadas (Año 1) | B11: 23000
A12: Costos Variables Totales Año 1 | B12: ='Estructura de costos'!C4 -> 3687.48
A13: Margen de Contribucion (23,000 - 3,687) | B13: =B11-B12 -> 19312.52
A14: Razon de Margen de Contribucion (17,313 / 23,000) | B14: =B13/B11 -> 0.83967478 | C14: 82.4%
A15: Costo Fijo Anual Año 1 | B15: ='Estructura de costos'!C3 -> 24456
A16: Costo Variable Unitario Equivalente (por solicitud procesada, Año 1: 3,687 / 7,000) | B16: =B12/'Estructura de costos'!B9 -> 0.52678286
A17: Precio Promedio por Solicitud Equivalente (23,000 / 7,000) | B17: =B11/'Estructura de costos'!B9 -> 3.2857143
A18: Punto de Equilibrio: 24,456 / (3.00 - 0.53) = 8864 solicitudes/año | B18: =B15/(B17-B16) -> 8864.3015 | C18: solicitudes/año
A22: Tabla 20. Proyección de demanda NEXIA a 5 años
A23: ='Estructura de costos'!A8 -> Año | B23: ='Estructura de costos'!B8 -> Solicitudes
A24: ='Estructura de costos'!A9 -> Año 1 | B24: ='Estructura de costos'!B9 -> 7000
A25: ='Estructura de costos'!A10 -> Año 2 | B25: ='Estructura de costos'!B10 -> 8000
A26: ='Estructura de costos'!A11 -> Año 3 | B26: ='Estructura de costos'!B11 -> 9000
A27: ='Estructura de costos'!A12 -> Año 4 | B27: ='Estructura de costos'!B12 -> 10000
A28: ='Estructura de costos'!A13 -> Año 5 | B28: ='Estructura de costos'!B13 -> 12000

Sheet FlujoCaja
A1: Tabla 21. Flujo de caja proyectado NEXIA — escenario de 5 años
A2: FLUJO DE CAJA PROYECTADO
B3: AÑO 0 | C3: AÑO 1 | D3: AÑO 2 | E3: AÑO 3 | F3: AÑO 4 | G3: AÑO 5
A4: Total de Ingresos | C4: ='Proyeccion de ingresos'!B11 -> 23000 | D4: =+C4+3000 -> 26000 | E4: =+D4+3000 -> 29000 | F4: =+E4+3000 -> 32000 | G4: =+F4+6000 -> 38000
A5: Costos Variables
A6: Total de costos variables anuales | C6: ='Preguntas adicionales a EC'!E10 -> 3687.48 | D6: ='Estructura de costos'!G10 -> 4504 | E6: ='Estructura de costos'!G11 -> 5505 | F6: ='Estructura de costos'!G12 -> 6380 | G6: ='Estructura de costos'!G13 -> 8130
A7: Mano de Obra Tecnica (2 dev + 1 QA parcial) | C7: 7200 | D7: 7200 | E7: 7200 | F7: 7200 | G7: 7200
A8: CIF (hosting, herramientas, marketing) | C8: 4068 | D8: 4068 | E8: 5868 | F8: 5868 | G8: 5868
A9: Total costos operativos | C9: =SUM(C6:C8) -> 14955.48 | D9: =SUM(D6:D8) -> 15772 | E9: =SUM(E6:E8) -> 18573 | F9: =SUM(F6:F8) -> 19448 | G9: =SUM(G6:G8) -> 21198
A10: Gastos Financieros
A11: Gastos de Sueldos Administrativos (QA soporte) | C11: 4800 | D11: 4800 | E11: 4800 | F11: 4800 | G11: 4800
A12: Gastos de Internet | C12: 360 | D12: 360 | E12: 360 | F12: 360 | G12: 360
A13: Gastos de energía eléctrica | C13: 480 | D13: 480 | E13: 120 | F13: 120 | G13: 120
A14: Gastos Software y Licencias (Vercel+Render+Supabase+GitHub) | C14: 840 | D14: 840 | E14: 840 | F14: 840 | G14: 840
A15: Alquiler Oficina/Coworking | C15: 0 | D15: 0 | E15: 1800 | F15: 1800 | G15: 1800
A16: Total Gastos Financieros | C16: =SUM(C11:C15) -> 6480 | D16: =SUM(D11:D15) -> 6480 | E16: =SUM(E11:E15) -> 7920 | F16: =SUM(F11:F15) -> 7920 | G16: =SUM(G11:G15) -> 7920
A17: UTILIDAD ANTES DE IMPUESOS | C17: =+C4-C9-C16 -> 1564.52 | D17: =+D4-D9-D16 -> 3748 | E17: =+E4-E9-E16 -> 2507 | F17: =+F4-F9-F16 -> 4632 | G17: =+G4-G9-G16 -> 8882
A18: Gastos de interes | C18: 0 | D18: 0 | E18: 0 | F18: 0 | G18: 0
A19: utilidad antes de participacion e impuestos | C19: =+C17 -> 1564.52 | D19: =+D17 -> 3748 | E19: =+E17 -> 2507 | F19: =+F17 -> 4632 | G19: =+G17 -> 8882
A20: 15% Participacion de trabajadores | C20: =+C19*15/100 -> 234.678 | D20: =+D19*15/100 -> 562.2 | E20: =+E19*15/100 -> 376.05 | F20: =+F19*15/100 -> 694.8 | G20: =+G19*15/100 -> 1332.3
A21: Utilidad antes de impuesto a la renta | C21: =+C19-C20 -> 1329.842 | D21: =+D19-D20 -> 3185.8 | E21: =+E19-E20 -> 2130.95 | F21: =+F19-F20 -> 3937.2 | G21: =+G19-G20 -> 7549.7
A23: Impuestos 25% | C23: =+C21*25/100 -> 332.4605 | D23: =+D21*25/100 -> 796.45 | E23: =+E21*25/100 -> 532.7375 | F23: =+F21*25/100 -> 984.3 | G23: =+G21*25/100 -> 1887.425
A24: Utilidada Neta | C24: =+C21-C23 -> 997.3815 | D24: =+D21-D23 -> 2389.35 | E24: =+E21-E23 -> 1598.2125 | F24: =+F21-F23 -> 2952.9 | G24: =+G21-G23 -> 5662.275
A25: Inversión en activos | B25: -8000
A26: Préstamo bancario | B26: 5000
A27: Amortización | C27: 818 | D27: =+C27*(1+0.08)^1 -> 883.44 | E27: =+D27*(1+0.08)^1 -> 954.1152 | F27: =+E27*(1+0.08)^1 -> 1030.4444 | G27: =+F27*(1+0.08)^1 -> 1112.88
A28: Capital de trabajo | B28: ='Estructura de costos'!L14 -> 3960
A29: Flujo de Caja | B29: =+(-8000+5000-3960) -> -6960 | C29: =+C24-C27 -> 179.3815 | D29: =+D24-D27 -> 1505.91 | E29: =+E24-E27 -> 644.0973 | F29: =+F24-F27 -> 1922.4556 | G29: =+G24-G27 -> 4549.395
A30: Tasa de Descuento | B30: 0.15
A31: VAN | B31: =NPV(B30,C29:G29)+B29 -> -1880.8038
A32: TIR | B32: =IRR(B29:G29) -> 0.060485822

Sheet VAN
A1: Tabla 21. Flujo de caja proyectado NEXIA
A2: Año | B2: Flujo Neto | C2: Factor Descuento (15%) | D2: Flujo Descontado
A3: 0 | B3: =FlujoCaja!B29 -> -6960 | C3: =1/(1+0.15)^A3 -> 1 | D3: =B3*C3 -> -6960
A4: 1 | B4: =FlujoCaja!C29 -> 179.3815 | C4: =1/(1+0.15)^A4 -> 0.86956522 | D4: =B4*C4 -> 155.98391
A5: 2 | B5: =FlujoCaja!D29 -> 1505.91 | C5: =1/(1+0.15)^A5 -> 0.75614367 | D5: =B5*C5 -> 1138.6843
A6: 3 | B6: =FlujoCaja!E29 -> 644.0973 | C6: =1/(1+0.15)^A6 -> 0.65751623 | D6: =B6*C6 -> 423.50443
A7: 4 | B7: =FlujoCaja!F29 -> 1922.4556 | C7: =1/(1+0.15)^A7 -> 0.57175325 | D7: =B7*C7 -> 1099.1702
A8: 5 | B8: =FlujoCaja!G29 -> 4549.395 | C8: =1/(1+0.15)^A8 -> 0.49717674 | D8: =B8*C8 -> 2261.8534
A9: VAN TOTAL | D9: =D3+(D4)+(D5)+(D6)+D7+(D8) -> -1880.8038

Sheet FlujoCajaVANAcelerado
A1: Tabla 23.Flujo de caja proyectado NEXIA acelerado con el cálculo del TIR en Excel
A2: FLUJO DE CAJA PROYECTADO
B3: AÑO 0 | C3: AÑO 1 | D3: AÑO 2 | E3: AÑO 3 | F3: AÑO 4 | G3: AÑO 5
A4: Total de Ingresos | C4: 28000 | D4: =35000 -> 35000 | E4: =+D4+3000 -> 38000 | F4: =+E4+3000 -> 41000 | G4: =+F4+6000 -> 47000
A5: Costos Variables
A6: Total de costos variables anuales | C6: ='Preguntas adicionales a EC'!E10 -> 3687.48 | D6: ='Estructura de costos'!G10 -> 4504 | E6: ='Estructura de costos'!G11 -> 5505 | F6: ='Estructura de costos'!G12 -> 6380 | G6: ='Estructura de costos'!G13 -> 8130
A7: Mano de Obra Tecnica (2 dev + 1 QA parcial) | C7: 7200 | D7: 7200 | E7: 7200 | F7: 7200 | G7: 7200
A8: CIF (hosting, herramientas, marketing) | C8: 4068 | D8: 4068 | E8: 5868 | F8: 5868 | G8: 5868
A9: Total costos operativos | C9: =SUM(C6:C8) -> 14955.48 | D9: =SUM(D6:D8) -> 15772 | E9: =SUM(E6:E8) -> 18573 | F9: =SUM(F6:F8) -> 19448 | G9: =SUM(G6:G8) -> 21198
A10: Gastos Financieros
A11: Gastos de Sueldos Administrativos (QA soporte) | C11: 4800 | D11: 4800 | E11: 4800 | F11: 4800 | G11: 4800
A12: Gastos de Internet | C12: 360 | D12: 360 | E12: 360 | F12: 360 | G12: 360
A13: Gastos de energía eléctrica | C13: 480 | D13: 480 | E13: 120 | F13: 120 | G13: 120
A14: Gastos Software y Licencias (Vercel+Render+Supabase+GitHub) | C14: 840 | D14: 840 | E14: 840 | F14: 840 | G14: 840
A15: Alquiler Oficina/Coworking | C15: 0 | D15: 0 | E15: 1800 | F15: 1800 | G15: 1800
A16: Total Gastos Financieros | C16: =SUM(C11:C15) -> 6480 | D16: =SUM(D11:D15) -> 6480 | E16: =SUM(E11:E15) -> 7920 | F16: =SUM(F11:F15) -> 7920 | G16: =SUM(G11:G15) -> 7920
A17: UTILIDAD ANTES DE IMPUESOS | C17: =+C4-C9-C16 -> 6564.52 | D17: =+D4-D9-D16 -> 12748 | E17: =+E4-E9-E16 -> 11507 | F17: =+F4-F9-F16 -> 13632 | G17: =+G4-G9-G16 -> 17882
A18: Gastos de interes | C18: 0 | D18: 0 | E18: 0 | F18: 0 | G18: 0
A19: utilidad antes de participacion e impuestos | C19: =+C17 -> 6564.52 | D19: =+D17 -> 12748 | E19: =+E17 -> 11507 | F19: =+F17 -> 13632 | G19: =+G17 -> 17882
A20: 15% Participacion de trabajadores | C20: =+C19*15/100 -> 984.678 | D20: =+D19*15/100 -> 1912.2 | E20: =+E19*15/100 -> 1726.05 | F20: =+F19*15/100 -> 2044.8 | G20: =+G19*15/100 -> 2682.3
A21: Utilidad antes de impuesto a la renta | C21: =+C19-C20 -> 5579.842 | D21: =+D19-D20 -> 10835.8 | E21: =+E19-E20 -> 9780.95 | F21: =+F19-F20 -> 11587.2 | G21: =+G19-G20 -> 15199.7
A23: Impuestos 25% | C23: =+C21*25/100 -> 1394.9605 | D23: =+D21*25/100 -> 2708.95 | E23: =+E21*25/100 -> 2445.2375 | F23: =+F21*25/100 -> 2896.8 | G23: =+G21*25/100 -> 3799.925
A24: Utilidada Neta | C24: =+C21-C23 -> 4184.8815 | D24: =+D21-D23 -> 8126.85 | E24: =+E21-E23 -> 7335.7125 | F24: =+F21-F23 -> 8690.4 | G24: =+G21-G23 -> 11399.775
A25: Inversión en activos | B25: -8000
A26: Préstamo bancario | B26: 5000
A27: Amortización | C27: 818 | D27: =+C27*(1+0.08)^1 -> 883.44 | E27: =+D27*(1+0.08)^1 -> 954.1152 | F27: =+E27*(1+0.08)^1 -> 1030.4444 | G27: =+F27*(1+0.08)^1 -> 1112.88
A28: Capital de trabajo | B28: ='Estructura de costos'!L14 -> 3960
A29: Flujo de Caja | B29: =+(-8000+5000-3960) -> -6960 | C29: =+C24-C27 -> 3366.8815 | D29: =+D24-D27 -> 7243.41 | E29: =+E24-E27 -> 6381.5973 | F29: =+F24-F27 -> 7659.9556 | G29: =+G24-G27 -> 10286.895
A30: Tasa de Descuento | B30: 0.15
A31: VAN | B31: =NPV(B30,C29:G29)+B29 -> 15134.795
A32: TIR | B32: =IRR(B29:G29) -> 0.7461581

Sheet VANAcelerado
A1: Tabla 24. Flujo de caja proyectado NEXIA
A2: Año | B2: Flujo Neto Acelerado | C2: Factor Descuento (15%) | D2: Flujo Descontado
A3: 0 | B3: =FlujoCajaVANAcelerado!B29 -> -6960 | C3: =1/(1+0.15)^A3 -> 1 | D3: =B3*C3 -> -6960
A4: 1 | B4: =FlujoCajaVANAcelerado!C29 -> 3366.8815 | C4: =1/(1+0.15)^A4 -> 0.86956522 | D4: =B4*C4 -> 2927.723
A5: 2 | B5: =FlujoCajaVANAcelerado!D29 -> 7243.41 | C5: =1/(1+0.15)^A5 -> 0.75614367 | D5: =B5*C5 -> 5477.0586
A6: 3 | B6: =FlujoCajaVANAcelerado!E29 -> 6381.5973 | C6: =1/(1+0.15)^A6 -> 0.65751623 | D6: =B6*C6 -> 4196.0038
A7: 4 | B7: =FlujoCajaVANAcelerado!F29 -> 7659.9556 | C7: =1/(1+0.15)^A7 -> 0.57175325 | D7: =B7*C7 -> 4379.6045
A8: 5 | B8: =FlujoCajaVANAcelerado!G29 -> 10286.895 | C8: =1/(1+0.15)^A8 -> 0.49717674 | D8: =B8*C8 -> 5114.4049
A9: VAN TOTAL (3 clientes año 1, crecimiento agresivo) | D9: =D3+(D4)+(D5)+(D6)+D7+(D8) -> 15134.795

Sheet Conclusión financiera
A1: Conclusión financiera
A2: NEXIA requiere una inversión inicial de $15.105. Gracias al uso de servicios gratuitos como Didit para verificaciones KYC, Google Gemini 2.5 Flash y plataformas cloud en sus planes gratuitos (Supabase, GitHub, Vercel, Render, Figma y Brevo), los costos operativos reales son menores a los estimados inicialmente. En el escenario base, el proyecto obtiene un VAN de -$1.880,80 y una TIR de 6%, resultados inferiores a la tasa de descuento del 15%, por lo que no alcanza la rentabilidad esperada. Sin embargo, en el escenario acelerado, mediante una mayor captación de clientes y crecimiento de ingresos recurrentes, el proyecto alcanza un VAN de $15.134,79 y una TIR de 75%, superando ampliamente la tasa de descuento y demostrando su viabilidad financiera. En consecuencia, la rentabilidad de NEXIA dependerá principalmente de la ejecución de su estrategia comercial y de su capacidad para captar y retener clientes durante los primeros años de funcionamiento.
